{
  "$schema": "http://json-schema.org/draft-07/schema#",

  "type": "object",
  "properties": {
    "location": {
      "markdownDescription": "The instance location.",
      "type": "string",
      "format": "json-pointer"
    },
    "keyword": {
      "markdownDescription": "The annotation keyword.",
      "type": "string"
    },
    "expected": {
      "markdownDescription": "An array of `keyword` annotations expected on the instance at `location`.",
      "type": "array"
    }
  },
  "required": ["location", "keyword", "expected"]
}
